src/__init__.py
src/app.py
bemle_pipelines-0.1.dist-info/LICENSE
bemle_pipelines-0.1.dist-info/METADATA
bemle_pipelines-0.1.dist-info/WHEEL
bemle_pipelines-0.1.dist-info/top_level.txt
bemle_pipelines-0.1.dist-info/RECORD
